{
  "schema": "config_v4",
  "generated": 1781213173469,
  "endpoints": [
    "/4Btuyb",
    "/wnTmMdA2"
  ],
  "limits": {
    "min": 3,
    "max": 1013
  },
  "wdETZM": 24206,
  "Ulh5ZW": 9138,
  "pkskde": 47659,
  "qdF5uP": 40430,
  "ufYzIQ": 36129,
  "XLiRMY": 47612,
  "mBM5F": "PZuJct0Z0A5r",
  "Yoz6WM": 5422,
  "sKpF0A": 48835,
  "swpEm": "UVS1BI13Wsi3",
  "bsRybK": 32005,
  "JPlwx": "s4296Y8LSHDA",
  "vs1fWp": 27200,
  "eVW9tt": 309,
  "SBEQGc": 18476,
  "FogOn": "EvQ895bvuVa7",
  "NWE1K9": 14799,
  "t8mwO": "H5LHiDjklXof",
  "nnmSeo": 26381,
  "H7yZV": "8af7FD3GYfGJ",
  "4sgRar": 1065,
  "leODGC": 11630,
  "CFwC5e": 6712,
  "LBk520": 46521,
  "nHlWo": "AkuLyBPjUysl",
  "akQ7lH": 42915,
  "dIHPy": "tQqwrFSb0XYC",
  "qoxSbb": 8905,
  "UwaY9V": 14680,
  "nWFAs": "KT4VyVOpPlc3",
  "dCVduo": 17087,
  "gYVFw": "Pad3j11n4M2X",
  "NqmX3w": 14070,
  "H5SUca": 45278,
  "CX6oc5": 45822,
  "KvkrR4": 542
}
/* final checksum */ const CHECKSUM = 465890;
